album/__init__.py
album/runner/__init__.py
album/runner/album_logging.py
album/runner/api.py
album/runner/core/__init__.py
album/runner/core/default_values_runner.py
album/runner/core/api/__init__.py
album/runner/core/api/model/__init__.py
album/runner/core/api/model/coordinates.py
album/runner/core/api/model/solution.py
album/runner/core/model/__init__.py
album/runner/core/model/coordinates.py
album/runner/core/model/solution.py
album/runner/core/model/solution_script.py
album/runner/core/schema/__init__.py
album/runner/core/schema/solution_schema.json
album_solution_api-0.7.0.dist-info/LICENSE
album_solution_api-0.7.0.dist-info/METADATA
album_solution_api-0.7.0.dist-info/WHEEL
album_solution_api-0.7.0.dist-info/top_level.txt
album_solution_api-0.7.0.dist-info/RECORD
