Metadata-Version: 2.1
Name: album-solution-api
Version: 0.7.0
Summary: Album is a framework for unifying computational tools across frameworks, languages, and environments.
Home-page: https://gitlab.com/album-app/album-solution-api
Author: Kyle Harrington, Jan Philipp Albrecht, Deborah Schmidt
Maintainer: Kyle Harrington, Jan Philipp Albrecht, Deborah Schmidt
Maintainer-email: album@kyleharrington.com
License: MIT
Project-URL: Source, https://gitlab.com/album-app/album-solution-api
Project-URL: Tracker, https://gitlab.com/album-app/album-solution-api/issues
Keywords: virtual,environments,imaging
Platform: any
Classifier: Development Status :: 3 - Alpha
Classifier: License :: OSI Approved :: MIT License
Classifier: Operating System :: MacOS :: MacOS X
Classifier: Operating System :: Microsoft :: Windows
Classifier: Operating System :: POSIX
Classifier: Programming Language :: Python :: 3.8
Classifier: Programming Language :: Python :: 3.9
Classifier: Programming Language :: Python :: Implementation :: PyPy
Classifier: Topic :: Utilities
Requires-Python: >=3.6
License-File: LICENSE
